post_review-1.3.0.dist-info/DESCRIPTION.rst
post_review-1.3.0.dist-info/METADATA
post_review-1.3.0.dist-info/RECORD
post_review-1.3.0.dist-info/WHEEL
post_review-1.3.0.dist-info/entry_points.txt
post_review-1.3.0.dist-info/metadata.json
post_review-1.3.0.dist-info/top_level.txt
postreview/BaseService.py
postreview/GitCommandRunner.py
postreview/GitHubService.py
postreview/GitLabService.py
postreview/GitServiceManager.py
postreview/GitUtils.py
postreview/__init__.py
postreview/__main__.py
postreview/cli.py
postreview/config.ini
postreview/configprocesser.py
postreview/logger.py
