Metadata-Version: 2.0
Name: post-review
Version: 1.3.0
Summary: unified command line interface for posting code reviews and merge requests
Home-page: https://github.com/ericforbes/post-review
Author: Eric Forbes
Author-email: ericforbes91@gmail.com
License: MIT
Keywords: git devops review
Platform: UNKNOWN
Classifier: Development Status :: 5 - Production/Stable
Classifier: Intended Audience :: Developers
Classifier: Intended Audience :: System Administrators
Classifier: License :: OSI Approved :: MIT License
Classifier: Natural Language :: English
Classifier: Programming Language :: Python
Classifier: Programming Language :: Python :: 2.7
Classifier: Programming Language :: Python :: 3.6
Classifier: Topic :: Software Development :: Version Control :: Git
Requires-Python: >=2.7,!=3.0.*,!=3.1.*,!=3.2.*,<4
Requires-Dist: coloredlogs (>=7.1)
Requires-Dist: configparser (>=3.5.0)
Requires-Dist: future (>=0.16.0)
Requires-Dist: requests (>=2.18)
